Metadata-Version: 1.1
Name: embtest
Version: 0.0.1
Summary: A light-weight testing module that enables users to write testing code along writing the actual code
Home-page: https://github.com/ColinQiyangLi/embtest
Author: Qiyang Li
Author-email: colin.qiyang.li@gmail.com
License: UNKNOWN
Platform: UNKNOWN
Classifier: Programming Language :: Python
Classifier: Programming Language :: Python :: 3
Classifier: License :: OSI Approved :: GNU General Public License (GPL)
Classifier: Operating System :: OS Independent
Classifier: Development Status :: 1 - Planning
Classifier: Environment :: Console
Classifier: Intended Audience :: Science/Research
Classifier: Topic :: Scientific/Engineering :: GIS
